aih_codegen/__init__.py
aih_codegen/generate.py
aih_codegen/template.py
aih_codegen-0.13.data/scripts/aih
aih_codegen-0.13.dist-info/METADATA
aih_codegen-0.13.dist-info/WHEEL
aih_codegen-0.13.dist-info/top_level.txt
aih_codegen-0.13.dist-info/RECORD
