Metadata-Version: 2.1
Name: aih-codegen
Version: 0.13
Summary: Generate graphql code
Home-page: https://github.com/quyencao/aih_codegen
Author: aih
Author-email: quyen.cm@example.com
License: MIT
Platform: UNKNOWN
Requires-Python: >=3.6
Requires-Dist: JinJa2
Requires-Dist: six
Requires-Dist: PyYAML
